streamlit_custom_toggle/__init__.py
streamlit_custom_toggle/frontend/build/asset-manifest.json
streamlit_custom_toggle/frontend/build/bootstrap.min.css
streamlit_custom_toggle/frontend/build/index.html
streamlit_custom_toggle/frontend/build/precache-manifest.7d22a7303f2ffca32e7ab45d297e4403.js
streamlit_custom_toggle/frontend/build/service-worker.js
streamlit_custom_toggle/frontend/build/static/js/2.7b19a51b.chunk.js
streamlit_custom_toggle/frontend/build/static/js/2.7b19a51b.chunk.js.LICENSE.txt
streamlit_custom_toggle/frontend/build/static/js/2.7b19a51b.chunk.js.map
streamlit_custom_toggle/frontend/build/static/js/main.181af669.chunk.js
streamlit_custom_toggle/frontend/build/static/js/main.181af669.chunk.js.map
streamlit_custom_toggle/frontend/build/static/js/runtime-main.3a596aa5.js
streamlit_custom_toggle/frontend/build/static/js/runtime-main.3a596aa5.js.map
streamlit_custom_toggle-0.1.1.dist-info/LICENSE
streamlit_custom_toggle-0.1.1.dist-info/METADATA
streamlit_custom_toggle-0.1.1.dist-info/WHEEL
streamlit_custom_toggle-0.1.1.dist-info/top_level.txt
streamlit_custom_toggle-0.1.1.dist-info/RECORD
